renv/__init__.py
renv/cookies/__init__.py
renv/cookies/init/cookiecutter.json
renv/cookies/init/{{cookiecutter.renv_init_dir}}/cran/.gitkeep
renv/cookies/nt/cookiecutter.json
renv/cookies/nt/{{cookiecutter.dirname}}/.Renviron
renv/cookies/nt/{{cookiecutter.dirname}}/.Rprofile
renv/cookies/nt/{{cookiecutter.dirname}}/Activate.ps.1
renv/cookies/nt/{{cookiecutter.dirname}}/activate
renv/cookies/nt/{{cookiecutter.dirname}}/activate.bat
renv/cookies/nt/{{cookiecutter.dirname}}/deactivate.bat
renv/cookies/posix/cookiecutter.json
renv/cookies/posix/{{cookiecutter.dirname}}/.Renviron
renv/cookies/posix/{{cookiecutter.dirname}}/.Rprofile
renv/cookies/posix/{{cookiecutter.dirname}}/Renviron.site
renv/cookies/posix/{{cookiecutter.dirname}}/Rprofile.site
renv/cookies/posix/{{cookiecutter.dirname}}/activate
renv/cookies/posix/{{cookiecutter.dirname}}/activate.csh
renv/cookies/posix/{{cookiecutter.dirname}}/activate.fish
renv/core.py
renv/renv.py
renv/utils.py
renv-0.3.1.dist-info/entry_points.txt
renv-0.3.1.dist-info/LICENSE
renv-0.3.1.dist-info/WHEEL
renv-0.3.1.dist-info/METADATA
renv-0.3.1.dist-info/RECORD
